chstides/__init__.py
chstides/chs_iwls.py
chstides/const.py
pychs/__init__.py
pychs/chs_iwls.py
pychs/classes.py
pychs/const.py
chstides-0.3.2.dist-info/LICENSE.txt
chstides-0.3.2.dist-info/METADATA
chstides-0.3.2.dist-info/WHEEL
chstides-0.3.2.dist-info/top_level.txt
chstides-0.3.2.dist-info/RECORD
