Metadata-Version: 2.1
Name: chstides
Version: 0.3.2
Summary: Python Wrapper for Canadian Hydrographic Service (CHS) Integrated Water Level System API
Home-page: https://github.com/RonSchofield/chs-tides
Author: Ron Schofield
Author-email: ronschofield@eastlink.ca
Classifier: Programming Language :: Python :: 3
Classifier: License :: OSI Approved :: MIT License
Classifier: Operating System :: OS Independent
Requires-Python: >=3.6
License-File: LICENSE.txt
Requires-Dist: aiohttp
Requires-Dist: geopy
Requires-Dist: voluptuous
